fontcrunch/_quadopt.cpython-37m-x86_64-linux-gnu.so
fontcrunch/fontcrunch.py
fontcrunch/__init__.py
fontcrunch/_version.py
fontcrunch/cli.py
FontCrunch-0.1.0rc1.dist-info/AUTHORS
FontCrunch-0.1.0rc1.dist-info/WHEEL
FontCrunch-0.1.0rc1.dist-info/top_level.txt
FontCrunch-0.1.0rc1.dist-info/entry_points.txt
FontCrunch-0.1.0rc1.dist-info/RECORD
FontCrunch-0.1.0rc1.dist-info/METADATA
FontCrunch-0.1.0rc1.dist-info/LICENSE
