Metadata-Version: 2.1
Name: FontCrunch
Version: 0.1.0rc1
Summary: fontcrunch
Home-page: https://github.com/googlefonts/fontcrunch/
Author: Raph Levien
Author-email: raph@google.com
License: Apache Software License 2.0
Platform: UNKNOWN
Classifier: Environment :: Console
Classifier: Intended Audience :: Developers
Classifier: License :: OSI Approved :: Apache Software License
Classifier: Operating System :: OS Independent
Classifier: Programming Language :: Python
Classifier: Topic :: Multimedia :: Graphics
Classifier: Topic :: Multimedia :: Graphics :: Graphics Conversion
Classifier: Topic :: Multimedia :: Graphics :: Editors :: Vector-Based
Requires-Dist: fonttools
Provides-Extra: plot
Requires-Dist: reportlab ; extra == 'plot'
